{
  "kind": "singleType",
  "collectionName": "footers",
  "info": {
    "singularName": "footer",
    "pluralName": "footers",
    "displayName": "Footer",
    "description": ""
  },
  "options": {
    "draftAndPublish": true
  },
  "pluginOptions": {},
  "attributes": {
    "topFooter": {
      "type": "component",
      "repeatable": true,
      "component": "content-block.top-footer"
    },
    "logoSection": {
      "type": "component",
      "repeatable": true,
      "component": "content-block.logo-section"
    },
    "younite": {
      "type": "component",
      "repeatable": false,
      "component": "content-block.younite"
    },
    "CreditsPrivacy": {
      "type": "string"
    }
  }
}
